{
  "id": "exalteddemake",
  "title": "Exalted Demake Edition",
  "description": "Unofficial Exalted demake edition system module for FoundryVTT!  Portions of the materials are the copyrights and trademarks of Paradox Interactive AB, and are used with permission. All rights reserved. For more information please visit worldofdarkness.com.",
  "url": "https://github.com/Aliharu/Foundry-ExD",
  "license": "LICENSE.txt",
  "version": "1.0.5",
  "compatibility": {
    "minimum": "10"
  },
  "esmodules": [
    "module/exalteddemake.js"
  ],
  "styles": [
    "css/exalteddemake.css"
  ],
  "languages": [
    {
      "lang": "en",
      "name": "English",
      "path": "lang/en.json",
      "flags": {}
    }
  ],
  "relationships": [],
  "manifest": "https://raw.githubusercontent.com/Aliharu/Foundry-ExD/master/system.json",
  "download": "https://github.com/Aliharu/Foundry-ExD/releases/download/v1.0.5/release1.0.5.zip",
  "gridDistance": 5,
  "gridUnits": "ft",
  "primaryTokenAttribute": "health",
  "secondaryTokenAttribute": "damage"
}